grbackup-1.1.dist-info/DESCRIPTION.rst
grbackup-1.1.dist-info/pydist.json
grbackup-1.1.dist-info/RECORD
grbackup-1.1.dist-info/METADATA
grbackup-1.1.dist-info/top_level.txt
grbackup-1.1.dist-info/WHEEL
grbackup-1.1.dist-info/entry_points.txt
grbackup/__init__.py
grbackup/grbackup.py
grbackup/greader.py
grbackup/grb_plugins/__init__.py
grbackup/grb_plugins/mongodb_output.py
grbackup/grb_plugins/redis_output.py
grbackup/grb_plugins/simple_output.py
grbackup/grb_plugins/json_output.py
grbackup-1.1.data/scripts/grbackup
