Metadata-Version: 2.0
Name: grbackup
Version: 1.1
Summary: Utilite to backup items from Google Reader
Home-page: https://bitbucket.org/wistful/grbackup
Author: wistful
Author-email: wst.public.mail@gmail.com
License: MIT License
Keywords: greader,backup
Platform: Unix,
Classifier: Development Status :: 5 - Production/Stable
Classifier: Environment :: Console
Classifier: Intended Audience :: Developers
Classifier: License :: OSI Approved :: MIT License
Classifier: Programming Language :: Python :: 2 :: Only
Classifier: Topic :: System :: Archiving :: Backup
Classifier: Topic :: Utilities
Requires-Dist: pymongo (>=2.4)
Requires-Dist: redis
